indexedheap/__init__.py
indexedheap/heap_item.py
indexedheap/indexed_heap.py
indexedheap-0.1.1.dist-info/METADATA
indexedheap-0.1.1.dist-info/WHEEL
indexedheap-0.1.1.dist-info/licenses/LICENSE
indexedheap-0.1.1.dist-info/RECORD
