Metadata-Version: 2.4
Name: indexedheap
Version: 0.1.1
Summary: Python MinHeap and MaxHeap implementation with arbitrary-value removal, frequency tracking for duplicates, and sorted iteration.
Project-URL: Source, https://github.com/Ite-O/python-indexed-heap
Project-URL: Issues, https://github.com/Ite-O/python-indexed-heap/issues
Author-email: iteo <oitedev@gmail.com>
License-Expression: MIT
License-File: LICENSE
Keywords: heap,index heap,indexed heap,indexed priority queue,indexedheap,max heap,max-heap,maxheap,min heap,min-heap,minheap,priority queue,priority-queue,priorityqueue
Classifier: License :: OSI Approved :: MIT License
Classifier: Operating System :: OS Independent
Classifier: Programming Language :: Python :: 3
Requires-Python: >=3.6
